saio.py
saio-0.2.1.dist-info/LICENSE
saio-0.2.1.dist-info/METADATA
saio-0.2.1.dist-info/WHEEL
saio-0.2.1.dist-info/top_level.txt
saio-0.2.1.dist-info/RECORD
