Metadata-Version: 2.1
Name: saio
Version: 0.2.1
Summary: SQLAlchemyIO (saio): Module hack for autoloading table definitions as ORM
Home-page: https://github.com/coroa/saio
Author: Jonas Hörsch
Author-email: coroa@posteo.de
License: MIT License
Project-URL: Bug Reports, https://github.com/coroa/saio/issues
Project-URL: Source, https://github.com/coroa/saio/
Platform: UNKNOWN
Classifier: Development Status :: 4 - Beta
Classifier: Intended Audience :: Developers
Classifier: Topic :: Software Development :: Build Tools
Classifier: License :: OSI Approved :: MIT License
Classifier: Programming Language :: Python :: 3
Classifier: Programming Language :: Python :: 3.4
Classifier: Programming Language :: Python :: 3.5
Classifier: Programming Language :: Python :: 3.6
Classifier: Programming Language :: Python :: 3.7
Requires-Python: >=3.4, <4
Requires-Dist: sqlalchemy
